setup.py
git_annex_remote_qcloud/__init__.py
git_annex_remote_qcloud/main.py
git_annex_remote_qcloud.egg-info/PKG-INFO
git_annex_remote_qcloud.egg-info/SOURCES.txt
git_annex_remote_qcloud.egg-info/dependency_links.txt
git_annex_remote_qcloud.egg-info/entry_points.txt
git_annex_remote_qcloud.egg-info/requires.txt
git_annex_remote_qcloud.egg-info/top_level.txt