Metadata-Version: 1.1
Name: git-annex-remote-qcloud
Version: 0.1.3
Summary: git-annex external special remote protocol for qcloud (Tencent Cloud).
Home-page: https://github.com/foreverbell/git-annex-remote-qcloud
Author: foreverbell
Author-email: dql.foreverbell@gmail.com
License: MIT
Keywords: git-annex qcloud
Platform: UNKNOWN
Classifier: Development Status :: 3 - Alpha
Classifier: Programming Language :: Python :: 2.7
